<?xml version="1.0" encoding="utf-8" ?>
<dwsync>
<file name="MMHTTPDB.php" server="D:/new/wamp/www/ims/" local="130079249298281250" remote="130079249290000000" Dst="0" />
<file name="mysql.php" server="D:/new/wamp/www/ims/" local="130079249298437500" remote="130079249290000000" Dst="0" />
<file name="MMHTTPDB.php" server="C:/wamp/www/ims/" local="130079249298281250" remote="130079249290000000" Dst="0" />
<file name="mysql.php" server="C:/wamp/www/ims/" local="130079249298437500" remote="130079249290000000" Dst="0" />
<file name="MMHTTPDB.php" server="C:/wamp/www/nfs/" local="130079249298281250" remote="130079249290000000" Dst="0" />
<file name="mysql.php" server="C:/wamp/www/nfs/" local="130079249298437500" remote="130079249290000000" Dst="0" />
<file name="MMHTTPDB.php" server="C:/wamp/www/hanbros/" local="130079249298281250" remote="130079249290000000" Dst="0" />
<file name="mysql.php" server="C:/wamp/www/hanbros/" local="130079249298437500" remote="130079249290000000" Dst="0" />
<file name="MMHTTPDB.php" server="C:/wamp/www/hanbrosadmin/" local="130079249300000000" remote="130079249300000000" Dst="0" />
<file name="mysql.php" server="C:/wamp/www/hanbrosadmin/" local="130079249300000000" remote="130079249300000000" Dst="0" />
<file name="MMHTTPDB.php" server="C:/wamp/www/cleaningadmin/" local="130079249300000000" remote="130079249300000000" Dst="0" />
<file name="mysql.php" server="C:/wamp/www/cleaningadmin/" local="130079249300000000" remote="130079249300000000" Dst="0" />
</dwsync>